README.rst
setup.py
funclib/__init__.py
funclib/funclib.py
funclib/funclib_conf.py
funclib.egg-info/PKG-INFO
funclib.egg-info/SOURCES.txt
funclib.egg-info/dependency_links.txt
funclib.egg-info/top_level.txt